hadder2.v
module hadder2 (
    input a,b,c,
    output sum,carry
);
wire halfsum;
wire halfcarry;
wire fullc;
    hadder Ha1(a,b,halfsum,halfcarry);
    hadder Ha2(halfsum,c,sum,fullc);
    assign carry=halfcarry|fullc;

endmodule

module hadder (
    input a,b,
    output sum,carry
);
assign sum = a ^ b;
assign carry = (a&b);
    
endmodule

tb_2hadder.v
module tb_2hadder;
    reg a,b,c;
    wire sum,carry;
    hadder2 uut(.a(a),.b(b),.c(c),.sum(sum),.carry(carry));
    initial begin
        $dumpfile("hadder2_.vcd");
        $dumpvars(0,tb_2hadder);
        #10;
        a=0;b=0;c=0;#10;
        a=0;b=0;c=1;#10;
        a=0;b=1;c=0;#10;
        a=0;b=1;c=1;#10;
        a=1;b=0;c=0;#10;
        a=1;b=0;c=1;#10;
        a=1;b=1;c=0;#10;
        a=1;b=1;c=1;#10;
        $finish;
    end
endmodule

hadder2_.vcd
$date
	Sat Aug 02 10:10:54 2025
$end
$version
	Icarus Verilog
$end
$timescale
	1s
$end
$scope module tb_2hadder $end
$var wire 1 ! sum $end
$var wire 1 " carry $end
$var reg 1 # a $end
$var reg 1 $ b $end
$var reg 1 % c $end
$scope module uut $end
$var wire 1 # a $end
$var wire 1 $ b $end
$var wire 1 % c $end
$var wire 1 " carry $end
$var wire 1 ! sum $end
$var wire 1 & halfsum $end
$var wire 1 ' halfcarry $end
$var wire 1 ( fullc $end
$scope module Ha1 $end
$var wire 1 # a $end
$var wire 1 $ b $end
$var wire 1 ' carry $end
$var wire 1 & sum $end
$upscope $end
$scope module Ha2 $end
$var wire 1 & a $end
$var wire 1 % b $end
$var wire 1 ( carry $end
$var wire 1 ! sum $end
$upscope $end
$upscope $end
$upscope $end
$enddefinitions $end
$comment Show the parameter values. $end
$dumpall
$end
#0
$dumpvars
x(
x'
x&
x%
x$
x#
x"
x!
$end
#10
0"
0!
0(
0&
0'
0%
0$
0#
#20
1!
1%
#30
1&
0%
1$
#40
1"
0!
1(
1%
#50
0"
1!
0(
0%
0$
1#
#60
1"
0!
1(
1%
#70
0(
0&
1'
0%
1$
#80
1!
1%
